roerich/__init__.py
roerich/dataset.py
roerich/helper.py
roerich/utils.py
roerich/viz.py
roerich/algorithms/__init__.py
roerich/algorithms/algorithms.py
roerich/algorithms/cpdc.py
roerich/algorithms/cpdc_cv.py
roerich/algorithms/enrg_dist.py
roerich/algorithms/matrix.py
roerich/algorithms/models.py
roerich/algorithms/net.py
roerich/algorithms/scaler.py
roerich/change_point/__init__.py
roerich/change_point/onnc.py
roerich/change_point/onnr.py
roerich/change_point/windows.py
roerich/density_ratio/__init__.py
roerich/explanation/__init__.py
roerich/metrics/__init__.py
roerich/metrics/metrics.py
roerich/metrics/pr.py
roerich/networks/__init__.py
roerich/scores/__init__.py
roerich/scores/energy.py
roerich/scores/fd.py
roerich/scores/mmd.py
roerich-0.6.0.dist-info/LICENSE
roerich-0.6.0.dist-info/METADATA
roerich-0.6.0.dist-info/WHEEL
roerich-0.6.0.dist-info/top_level.txt
roerich-0.6.0.dist-info/RECORD
