Metadata-Version: 2.1
Name: roerich
Version: 0.6.0
Summary: Change point detection.
Home-page: https://github.com/HSE-LAMBDA/roerich
Author: Mikhail Hushchyn, Kenenbek Arzymatov
Author-email: hushchyn.mikhail@gmail.com, kenenbek@gmail.com
License: BSD-2-Clause
Project-URL: Documentation, https://hse-lambda.github.io/roerich/
Project-URL: Source, https://github.com/HSE-LAMBDA/roerich/
Keywords: python,machine learning,neural networks,signal processing,segmentation,time series analysis,anomaly detection,change point detection,density ratio
Classifier: Intended Audience :: Science/Research
Classifier: Topic :: Scientific/Engineering
Classifier: Programming Language :: Python :: 3
Classifier: License :: OSI Approved :: BSD License
Classifier: Operating System :: OS Independent
Requires-Python: >=3.6
License-File: LICENSE
Requires-Dist: numpy (>=1.23.0)
Requires-Dist: pandas (>=1.4.2)
Requires-Dist: scipy (>=1.8.1)
Requires-Dist: scikit-learn (>=1.1.1)
Requires-Dist: joblib (>=1.1.0)
Requires-Dist: matplotlib (>=3.5.2)
Requires-Dist: torch (>=1.11.0)
Requires-Dist: torchaudio (>=0.11.0)
Requires-Dist: torchvision (>=0.12.0)
